promediathek/__init__.py
promediathek/converter.py
promediathek/downloader.py
promediathek/baseclass/__init__.py
promediathek/baseclass/api.py
promediathek/baseclass/audio.py
promediathek/baseclass/downloader.py
promediathek/baseclass/provider.py
promediathek/baseclass/subtitle.py
promediathek/baseclass/video.py
promediathek/download_protocols/__init__.py
promediathek/download_protocols/dash.py
promediathek/download_protocols/hls.py
promediathek/drm/__init__.py
promediathek/drm/basic_drm.py
promediathek/drm/playready.py
promediathek/drm/pssh.py
promediathek/drm/widevine.py
promediathek/ffmpeg/__init__.py
promediathek/ffmpeg/ffmpeg.py
promediathek/ffmpeg/utils.py
promediathek/pakete/__init__.py
promediathek/pakete/bestandspaket.py
promediathek/pakete/progresspaket.py
promediathek/pakete/sammelpaket.py
promediathek/utils/__init__.py
promediathek/utils/cli.py
promediathek/utils/db.py
promediathek/utils/logger.py
promediathek/utils/networking.py
promediathek/utils/oauth2.py
promediathek/utils/pythonlib.py
promediathek/utils/threader.py
promediathek-0.1.1.dist-info/licenses/LICENSE
promediathek-0.1.1.dist-info/METADATA
promediathek-0.1.1.dist-info/WHEEL
promediathek-0.1.1.dist-info/top_level.txt
promediathek-0.1.1.dist-info/RECORD
