Metadata-Version: 2.4
Name: promediathek
Version: 0.1.1
Summary: Framework for downloading Streaming Providers.
Author-email: Jan Erik Mühlwald <problemo@problemo.pro>
License-Expression: GPL-3.0-only
Project-URL: Homepage, https://github.com/Problemo57/promediathek
Project-URL: Issues, https://github.com/Problemo57/promediathek/issues
Classifier: Programming Language :: Python :: 3
Classifier: Operating System :: OS Independent
Requires-Python: >=3.9
License-File: LICENSE
Requires-Dist: promediapaket
Requires-Dist: pywidevine
Requires-Dist: pyplayready
Requires-Dist: mpegdash
Requires-Dist: pycryptodome
Dynamic: license-file
